obnpy2/Callback.py
obnpy2/__init__.py
obnpy2/obnextapi.py
obnpy2/obnnode.py
obnpy2-1.0.1.dist-info/METADATA
obnpy2-1.0.1.dist-info/WHEEL
obnpy2-1.0.1.dist-info/top_level.txt
obnpy2-1.0.1.dist-info/RECORD
